{
    "version": "https://jsonfeed.org/version/1",
    "title": "homepage • All posts by \"config配置类\" tag",
    "description": "欢迎来我的博客空间",
    "home_page_url": "https://pigpigletsgo.github.io/homepage",
    "items": [
        {
            "id": "https://pigpigletsgo.github.io/homepage/2024/03/03/computer-science/java/config%E9%85%8D%E7%BD%AE%E7%B1%BB/redis%E9%85%8D%E7%BD%AE%E7%B1%BB/",
            "url": "https://pigpigletsgo.github.io/homepage/2024/03/03/computer-science/java/config%E9%85%8D%E7%BD%AE%E7%B1%BB/redis%E9%85%8D%E7%BD%AE%E7%B1%BB/",
            "title": "redis配置类",
            "date_published": "2024-03-03T03:39:25.050Z",
            "content_html": "<figure class=\"highlight java\"><figcaption data-lang=\"java\"></figcaption><table><tr><td data-num=\"1\"></td><td><pre><span class=\"token annotation punctuation\">@Configuration</span></pre></td></tr><tr><td data-num=\"2\"></td><td><pre><span class=\"token keyword\">public</span> <span class=\"token keyword\">class</span> <span class=\"token class-name\">RedisConfig</span> <span class=\"token punctuation\">&#123;</span></pre></td></tr><tr><td data-num=\"3\"></td><td><pre></pre></td></tr><tr><td data-num=\"4\"></td><td><pre>    <span class=\"token annotation punctuation\">@Bean</span></pre></td></tr><tr><td data-num=\"5\"></td><td><pre>    <span class=\"token annotation punctuation\">@SuppressWarnings</span><span class=\"token punctuation\">(</span>value <span class=\"token operator\">=</span> <span class=\"token punctuation\">&#123;</span> <span class=\"token string\">\"unchecked\"</span><span class=\"token punctuation\">,</span> <span class=\"token string\">\"rawtypes\"</span> <span class=\"token punctuation\">&#125;</span><span class=\"token punctuation\">)</span></pre></td></tr><tr><td data-num=\"6\"></td><td><pre>    <span class=\"token keyword\">public</span> <span class=\"token class-name\">RedisTemplate</span><span class=\"token generics\"><span class=\"token punctuation\">&lt;</span><span class=\"token class-name\">Object</span><span class=\"token punctuation\">,</span> <span class=\"token class-name\">Object</span><span class=\"token punctuation\">></span></span> <span class=\"token function\">redisTemplate</span><span class=\"token punctuation\">(</span><span class=\"token class-name\">RedisConnectionFactory</span> connectionFactory<span class=\"token punctuation\">)</span></pre></td></tr><tr><td data-num=\"7\"></td><td><pre>    <span class=\"token punctuation\">&#123;</span></pre></td></tr><tr><td data-num=\"8\"></td><td><pre>        <span class=\"token class-name\">RedisTemplate</span><span class=\"token generics\"><span class=\"token punctuation\">&lt;</span><span class=\"token class-name\">Object</span><span class=\"token punctuation\">,</span> <span class=\"token class-name\">Object</span><span class=\"token punctuation\">></span></span> template <span class=\"token operator\">=</span> <span class=\"token keyword\">new</span> <span class=\"token class-name\">RedisTemplate</span><span class=\"token generics\"><span class=\"token punctuation\">&lt;</span><span class=\"token punctuation\">></span></span><span class=\"token punctuation\">(</span><span class=\"token punctuation\">)</span><span class=\"token punctuation\">;</span></pre></td></tr><tr><td data-num=\"9\"></td><td><pre>        template<span class=\"token punctuation\">.</span><span class=\"token function\">setConnectionFactory</span><span class=\"token punctuation\">(</span>connectionFactory<span class=\"token punctuation\">)</span><span class=\"token punctuation\">;</span></pre></td></tr><tr><td data-num=\"10\"></td><td><pre></pre></td></tr><tr><td data-num=\"11\"></td><td><pre>        <span class=\"token class-name\">FastJsonRedisSerializer</span> serializer <span class=\"token operator\">=</span> <span class=\"token keyword\">new</span> <span class=\"token class-name\">FastJsonRedisSerializer</span><span class=\"token punctuation\">(</span><span class=\"token class-name\">Object</span><span class=\"token punctuation\">.</span><span class=\"token keyword\">class</span><span class=\"token punctuation\">)</span><span class=\"token punctuation\">;</span></pre></td></tr><tr><td data-num=\"12\"></td><td><pre></pre></td></tr><tr><td data-num=\"13\"></td><td><pre>        <span class=\"token comment\">// 使用 StringRedisSerializer 来序列化和反序列化 redis 的 key 值</span></pre></td></tr><tr><td data-num=\"14\"></td><td><pre>        template<span class=\"token punctuation\">.</span><span class=\"token function\">setKeySerializer</span><span class=\"token punctuation\">(</span><span class=\"token keyword\">new</span> <span class=\"token class-name\">StringRedisSerializer</span><span class=\"token punctuation\">(</span><span class=\"token punctuation\">)</span><span class=\"token punctuation\">)</span><span class=\"token punctuation\">;</span></pre></td></tr><tr><td data-num=\"15\"></td><td><pre>        template<span class=\"token punctuation\">.</span><span class=\"token function\">setValueSerializer</span><span class=\"token punctuation\">(</span>serializer<span class=\"token punctuation\">)</span><span class=\"token punctuation\">;</span></pre></td></tr><tr><td data-num=\"16\"></td><td><pre></pre></td></tr><tr><td data-num=\"17\"></td><td><pre>        <span class=\"token comment\">// Hash 的 key 也采用 StringRedisSerializer 的序列化方式</span></pre></td></tr><tr><td data-num=\"18\"></td><td><pre>        template<span class=\"token punctuation\">.</span><span class=\"token function\">setHashKeySerializer</span><span class=\"token punctuation\">(</span><span class=\"token keyword\">new</span> <span class=\"token class-name\">StringRedisSerializer</span><span class=\"token punctuation\">(</span><span class=\"token punctuation\">)</span><span class=\"token punctuation\">)</span><span class=\"token punctuation\">;</span></pre></td></tr><tr><td data-num=\"19\"></td><td><pre>        template<span class=\"token punctuation\">.</span><span class=\"token function\">setHashValueSerializer</span><span class=\"token punctuation\">(</span>serializer<span class=\"token punctuation\">)</span><span class=\"token punctuation\">;</span></pre></td></tr><tr><td data-num=\"20\"></td><td><pre></pre></td></tr><tr><td data-num=\"21\"></td><td><pre>        template<span class=\"token punctuation\">.</span><span class=\"token function\">afterPropertiesSet</span><span class=\"token punctuation\">(</span><span class=\"token punctuation\">)</span><span class=\"token punctuation\">;</span></pre></td></tr><tr><td data-num=\"22\"></td><td><pre>        <span class=\"token keyword\">return</span> template<span class=\"token punctuation\">;</span></pre></td></tr><tr><td data-num=\"23\"></td><td><pre>    <span class=\"token punctuation\">&#125;</span></pre></td></tr><tr><td data-num=\"24\"></td><td><pre><span class=\"token punctuation\">&#125;</span></pre></td></tr></table></figure>",
            "tags": [
                "java",
                "计算机学科",
                "config配置类"
            ]
        },
        {
            "id": "https://pigpigletsgo.github.io/homepage/2024/03/03/computer-science/java/config%E9%85%8D%E7%BD%AE%E7%B1%BB/MyBatisPlus%E9%85%8D%E7%BD%AE%E7%B1%BB/",
            "url": "https://pigpigletsgo.github.io/homepage/2024/03/03/computer-science/java/config%E9%85%8D%E7%BD%AE%E7%B1%BB/MyBatisPlus%E9%85%8D%E7%BD%AE%E7%B1%BB/",
            "title": "MyBatisPlus配置类",
            "date_published": "2024-03-03T03:37:39.624Z",
            "content_html": "<figure class=\"highlight java\"><figcaption data-lang=\"java\"></figcaption><table><tr><td data-num=\"1\"></td><td><pre><span class=\"token annotation punctuation\">@Configuration</span></pre></td></tr><tr><td data-num=\"2\"></td><td><pre><span class=\"token annotation punctuation\">@MapperScan</span><span class=\"token punctuation\">(</span><span class=\"token string\">\"com.dkx.mapper\"</span><span class=\"token punctuation\">)</span></pre></td></tr><tr><td data-num=\"3\"></td><td><pre><span class=\"token keyword\">public</span> <span class=\"token keyword\">class</span> <span class=\"token class-name\">MybatisPlusConfig</span> <span class=\"token punctuation\">&#123;</span></pre></td></tr><tr><td data-num=\"4\"></td><td><pre>\t<span class=\"token comment\">/**</pre></td></tr><tr><td data-num=\"5\"></td><td><pre>\t * 新的分页插件</pre></td></tr><tr><td data-num=\"6\"></td><td><pre>\t * 需要设置 MybatisConfiguration#useDeprecatedExecutor = false</pre></td></tr><tr><td data-num=\"7\"></td><td><pre>\t * 避免缓存出现问题 (该属性会在旧插件移除后一同移除)</pre></td></tr><tr><td data-num=\"8\"></td><td><pre>\t */</span></pre></td></tr><tr><td data-num=\"9\"></td><td><pre>\t<span class=\"token annotation punctuation\">@Bean</span></pre></td></tr><tr><td data-num=\"10\"></td><td><pre>\t<span class=\"token keyword\">public</span> <span class=\"token class-name\">MybatisPlusInterceptor</span> <span class=\"token function\">mybatisPlusInterceptor</span><span class=\"token punctuation\">(</span><span class=\"token punctuation\">)</span> <span class=\"token punctuation\">&#123;</span></pre></td></tr><tr><td data-num=\"11\"></td><td><pre>\t\t<span class=\"token class-name\">MybatisPlusInterceptor</span> interceptor <span class=\"token operator\">=</span> <span class=\"token keyword\">new</span> <span class=\"token class-name\">MybatisPlusInterceptor</span><span class=\"token punctuation\">(</span><span class=\"token punctuation\">)</span><span class=\"token punctuation\">;</span></pre></td></tr><tr><td data-num=\"12\"></td><td><pre>\t\tinterceptor<span class=\"token punctuation\">.</span><span class=\"token function\">addInnerInterceptor</span><span class=\"token punctuation\">(</span><span class=\"token keyword\">new</span> <span class=\"token class-name\">PaginationInnerInterceptor</span><span class=\"token punctuation\">(</span><span class=\"token class-name\">DbType</span><span class=\"token punctuation\">.</span><span class=\"token constant\">MYSQL</span><span class=\"token punctuation\">)</span><span class=\"token punctuation\">)</span><span class=\"token punctuation\">;</span></pre></td></tr><tr><td data-num=\"13\"></td><td><pre>\t\t<span class=\"token keyword\">return</span> interceptor<span class=\"token punctuation\">;</span></pre></td></tr><tr><td data-num=\"14\"></td><td><pre>\t<span class=\"token punctuation\">&#125;</span></pre></td></tr><tr><td data-num=\"15\"></td><td><pre><span class=\"token punctuation\">&#125;</span></pre></td></tr></table></figure>",
            "tags": [
                "java",
                "计算机学科",
                "config配置类"
            ]
        }
    ]
}